HISTORY.rst
LICENSE.rst
MANIFEST.in
README.rst
setup.py
src/yafowil/__init__.py
src/yafowil.widget.recaptcha.egg-info/PKG-INFO
src/yafowil.widget.recaptcha.egg-info/SOURCES.txt
src/yafowil.widget.recaptcha.egg-info/dependency_links.txt
src/yafowil.widget.recaptcha.egg-info/entry_points.txt
src/yafowil.widget.recaptcha.egg-info/namespace_packages.txt
src/yafowil.widget.recaptcha.egg-info/not-zip-safe
src/yafowil.widget.recaptcha.egg-info/requires.txt
src/yafowil.widget.recaptcha.egg-info/top_level.txt
src/yafowil/widget/__init__.py
src/yafowil/widget/recaptcha/__init__.py
src/yafowil/widget/recaptcha/example.py
src/yafowil/widget/recaptcha/tests.py
src/yafowil/widget/recaptcha/widget.py
src/yafowil/widget/recaptcha/locales/yafowil.widget.recaptcha.pot
src/yafowil/widget/recaptcha/locales/de/LC_MESSAGES/yafowil.widget.recaptcha.mo
src/yafowil/widget/recaptcha/locales/de/LC_MESSAGES/yafowil.widget.recaptcha.po
src/yafowil/widget/recaptcha/locales/en/LC_MESSAGES/yafowil.widget.recaptcha.mo
src/yafowil/widget/recaptcha/locales/en/LC_MESSAGES/yafowil.widget.recaptcha.po
src/yafowil/widget/recaptcha/resources/recaptcha_ajax.js
src/yafowil/widget/recaptcha/resources/widget.js