Metadata-Version: 1.1
Name: yafowil.widget.recaptcha
Version: 1.2
Summary: reCAPTCHA widget for YAFOWIL
Home-page: https://github.com/bluedynamics/yafowil.widget.recaptcha
Author: BlueDynamics Alliance
Author-email: dev@bluedynamics.com
License: Simplified BSD
Platform: UNKNOWN
Classifier: Environment :: Web Environment
Classifier: Operating System :: OS Independent
Classifier: Programming Language :: Python
Classifier: Topic :: Internet :: WWW/HTTP :: Dynamic Content
Classifier: License :: OSI Approved :: BSD License
Classifier: Programming Language :: Python :: 2.7
Classifier: Programming Language :: Python :: 3.5
Classifier: Programming Language :: Python :: 3.6
Classifier: Programming Language :: Python :: 3.7
